LuFeixuechengJavaFangqiZhiLu/README.md
LuFeixuechengJavaFangqiZhiLu/__init__.py
LuFeixuechengJavaFangqiZhiLu/__main__.py
LuFeixuechengJavaFangqiZhiLu/file.epub
LuFeixuechengJavaFangqiZhiLu/index.html
LuFeixuechengJavaFangqiZhiLu/css/__init__.py
LuFeixuechengJavaFangqiZhiLu/css/annotations.css
LuFeixuechengJavaFangqiZhiLu/css/main.css
LuFeixuechengJavaFangqiZhiLu/css/normalize.css
LuFeixuechengJavaFangqiZhiLu/css/popup.css
LuFeixuechengJavaFangqiZhiLu/font/__init__.py
LuFeixuechengJavaFangqiZhiLu/font/fontello.eot
LuFeixuechengJavaFangqiZhiLu/font/fontello.svg
LuFeixuechengJavaFangqiZhiLu/font/fontello.ttf
LuFeixuechengJavaFangqiZhiLu/font/fontello.woff
LuFeixuechengJavaFangqiZhiLu/img/__init__.py
LuFeixuechengJavaFangqiZhiLu/img/annotator-glyph-sprite.png
LuFeixuechengJavaFangqiZhiLu/img/annotator-icon-sprite.png
LuFeixuechengJavaFangqiZhiLu/img/apple-touch-icon.png
LuFeixuechengJavaFangqiZhiLu/img/cancelfullscreen.png
LuFeixuechengJavaFangqiZhiLu/img/close.png
LuFeixuechengJavaFangqiZhiLu/img/fullscreen.png
LuFeixuechengJavaFangqiZhiLu/img/loader.gif
LuFeixuechengJavaFangqiZhiLu/img/menu-icon.png
LuFeixuechengJavaFangqiZhiLu/img/save.png
LuFeixuechengJavaFangqiZhiLu/img/saved.png
LuFeixuechengJavaFangqiZhiLu/img/settings-s.png
LuFeixuechengJavaFangqiZhiLu/img/settings.png
LuFeixuechengJavaFangqiZhiLu/img/star.png
LuFeixuechengJavaFangqiZhiLu/js/__init__.py
LuFeixuechengJavaFangqiZhiLu/js/epub.js
LuFeixuechengJavaFangqiZhiLu/js/epub.min.js
LuFeixuechengJavaFangqiZhiLu/js/epub.min.map
LuFeixuechengJavaFangqiZhiLu/js/hooks.min.js
LuFeixuechengJavaFangqiZhiLu/js/hooks.min.map
LuFeixuechengJavaFangqiZhiLu/js/reader.js
LuFeixuechengJavaFangqiZhiLu/js/reader.js.map
LuFeixuechengJavaFangqiZhiLu/js/reader.min.js
LuFeixuechengJavaFangqiZhiLu/js/reader.min.map
LuFeixuechengJavaFangqiZhiLu/js/hooks/__init__.py
LuFeixuechengJavaFangqiZhiLu/js/hooks/extensions/__init__.py
LuFeixuechengJavaFangqiZhiLu/js/hooks/extensions/highlight.js
lu_feixuecheng_java_fangqi_zhi_lu-2024.3.6.0.dist-info/METADATA
lu_feixuecheng_java_fangqi_zhi_lu-2024.3.6.0.dist-info/WHEEL
lu_feixuecheng_java_fangqi_zhi_lu-2024.3.6.0.dist-info/entry_points.txt
lu_feixuecheng_java_fangqi_zhi_lu-2024.3.6.0.dist-info/top_level.txt
lu_feixuecheng_java_fangqi_zhi_lu-2024.3.6.0.dist-info/RECORD
